{"cameraMode":{"drawMode":0,"name":"Shaded","section":"Shading Mode"},"sceneLighting":true,"audioPlay":false,"sceneViewState":{"showFog":true,"showMaterialUpdate":false,"showSkybox":true,"showFlares":true,"showImageEffects":true,"showParticleSystems":true},"in2DMode":false,"pivot":{"x":0.9616158604621887,"y":2.850337028503418,"z":4.890093803405762},"rotation":{"x":0.14978572726249696,"y":-0.8432840704917908,"z":0.30165737867355349,"w":0.4189634919166565},"size":0.44709330797195437,"orthographic":false}